cone.calendar-0.4-py3.9-nspkg.pth
cone/calendar/__init__.py
cone/calendar/interfaces.py
cone/calendar/tests.py
cone/calendar/browser/__init__.py
cone/calendar/browser/calendar.pt
cone/calendar/browser/calendar.py
cone/calendar/browser/static/calendar.css
cone/calendar/browser/static/calendar.js
cone/calendar/browser/static/calendar.min.js
cone/calendar/browser/static/fullcalendar/fullcalendar.css
cone/calendar/browser/static/fullcalendar/fullcalendar.js
cone/calendar/browser/static/fullcalendar/fullcalendar.min.css
cone/calendar/browser/static/fullcalendar/fullcalendar.min.js
cone/calendar/browser/static/fullcalendar/fullcalendar.print.css
cone/calendar/browser/static/fullcalendar/fullcalendar.print.min.css
cone/calendar/browser/static/fullcalendar/gcal.js
cone/calendar/browser/static/fullcalendar/gcal.min.js
cone/calendar/browser/static/fullcalendar/locale-all.js
cone/calendar/browser/static/fullcalendar/locale/af.js
cone/calendar/browser/static/fullcalendar/locale/ar-dz.js
cone/calendar/browser/static/fullcalendar/locale/ar-ly.js
cone/calendar/browser/static/fullcalendar/locale/ar-ma.js
cone/calendar/browser/static/fullcalendar/locale/ar-sa.js
cone/calendar/browser/static/fullcalendar/locale/ar-tn.js
cone/calendar/browser/static/fullcalendar/locale/ar.js
cone/calendar/browser/static/fullcalendar/locale/bg.js
cone/calendar/browser/static/fullcalendar/locale/ca.js
cone/calendar/browser/static/fullcalendar/locale/cs.js
cone/calendar/browser/static/fullcalendar/locale/da.js
cone/calendar/browser/static/fullcalendar/locale/de-at.js
cone/calendar/browser/static/fullcalendar/locale/de.js
cone/calendar/browser/static/fullcalendar/locale/el.js
cone/calendar/browser/static/fullcalendar/locale/en-au.js
cone/calendar/browser/static/fullcalendar/locale/en-ca.js
cone/calendar/browser/static/fullcalendar/locale/en-gb.js
cone/calendar/browser/static/fullcalendar/locale/en-ie.js
cone/calendar/browser/static/fullcalendar/locale/en-nz.js
cone_calendar-0.4.dist-info/licenses/LICENSE.rst
cone_calendar-0.4.dist-info/METADATA
cone_calendar-0.4.dist-info/WHEEL
cone_calendar-0.4.dist-info/namespace_packages.txt
cone_calendar-0.4.dist-info/top_level.txt
cone_calendar-0.4.dist-info/RECORD
