Metadata-Version: 2.4
Name: cone.calendar
Version: 0.4
Summary: jQuery Fullcalendar integration for cone.app
Home-page: http://github.com/conestack/cone.calendar
Author: Cone Contributors
Author-email: dev@conestack.org
License: Simplified BSD
Keywords: node pyramid cone web
Classifier: Environment :: Web Environment
Classifier: Programming Language :: Python
Classifier: Topic :: Internet :: WWW/HTTP :: Dynamic Content
License-File: LICENSE.rst
Requires-Dist: setuptools
Requires-Dist: cone.app<1.1.0
Requires-Dist: yafowil.widget.cron<2.0.0
Provides-Extra: test
Requires-Dist: zope.testrunner; extra == "test"
Dynamic: author
Dynamic: author-email
Dynamic: classifier
Dynamic: description
Dynamic: home-page
Dynamic: keywords
Dynamic: license
Dynamic: license-file
Dynamic: provides-extra
Dynamic: requires-dist
Dynamic: summary
